{
    "productName": "ArcanumMusic",
    "appId": "moe.nekozx.arcanummusic",
    "icon": "./public/AppIcon.ico",
    "files": [
        "./app/app.js",
        "./app/preload.mjs",
        "./app/fileManager.js",
        "./app/service.js",
        "./app/webSocket.js",
        "./dist"
    ],
    "directories": {
        "output": "./build"
    },
    "nsis": {
        "artifactName": "${productName}_${version}_Setup.${ext}",
        "shortcutName": "${productName}",
        "uninstallDisplayName": "${productName}",
        "installerIcon": "./dist/appIcon/AppIcon.ico",
        "uninstallerIcon": "./dist/appIcon/AppIcon.ico"
    }
}